gold_linear_regression.py
keras_experiment.py
linear_regression_example.py
preprocessor.py
ratio_encoder.py
target_builder.py
target_model.py
usa_csc_526_by_spc-1.0.0.data/data/LICENSE.txt
usa_csc_526_by_spc-1.0.0.data/data/README.txt
usa_csc_526_by_spc-1.0.0.data/data/pima-indians-diabetes.data.txt
usa_csc_526_by_spc-1.0.0.data/data/nasdaq_data/HistoricalData_1638400622722_gc_cmx.csv
usa_csc_526_by_spc-1.0.0.data/data/nasdaq_data/HistoricalData_1638400769169_si_cmx.csv
usa_csc_526_by_spc-1.0.0.data/data/nasdaq_data/HistoricalData_1638406866303_gld.csv
usa_csc_526_by_spc-1.0.0.data/data/nasdaq_data/HistoricalData_1638406929754_gldm.csv
usa_csc_526_by_spc-1.0.0.data/data/nasdaq_data/HistoricalData_1638407062013_eurusd.csv
usa_csc_526_by_spc-1.0.0.data/data/nasdaq_data/HistoricalData_1638407178132_spy.csv
usa_csc_526_by_spc-1.0.0.data/data/nasdaq_data/HistoricalData_1638407209538_spx.csv
usa_csc_526_by_spc-1.0.0.data/data/nasdaq_data/HistoricalData_1638407420724_eqrr.csv
usa_csc_526_by_spc-1.0.0.data/data/nasdaq_data/HistoricalData_1638407523735_smrrlx.csv
usa_csc_526_by_spc-1.0.0.data/data/nasdaq_data/HistoricalData_1638407571584_smrrmx.csv
usa_csc_526_by_spc-1.0.0.data/data/nasdaq_data/HistoricalData_1638407631127_buzz.csv
usa_csc_526_by_spc-1.0.0.data/data/nasdaq_data/HistoricalData_1638407654327_msez.csv
usa_csc_526_by_spc-1.0.0.data/data/nasdaq_data/HistoricalData_1638407684608_sent.csv
usa_csc_526_by_spc-1.0.0.data/data/nasdaq_data/HistoricalData_1638407741665_fshox.csv
usa_csc_526_by_spc-1.0.0.data/data/nasdaq_data/HistoricalData_1638407765609_mhpc.csv
usa_csc_526_by_spc-1.0.0.data/data/nasdaq_data/HistoricalData_1638407861057_bwx.csv
usa_csc_526_by_spc-1.0.0.data/data/nasdaq_data/HistoricalData_1638407888262_bwz.csv
usa_csc_526_by_spc-1.0.0.data/data/nasdaq_data/HistoricalData_1638407979358_pl_nmx.csv
usa_csc_526_by_spc-1.0.0.data/data/nasdaq_data/HistoricalData_1638408045510_mngg.csv
usa_csc_526_by_spc-1.0.0.dist-info/LICENSE.txt
usa_csc_526_by_spc-1.0.0.dist-info/METADATA
usa_csc_526_by_spc-1.0.0.dist-info/WHEEL
usa_csc_526_by_spc-1.0.0.dist-info/top_level.txt
usa_csc_526_by_spc-1.0.0.dist-info/RECORD
