Metadata-Version: 2.1
Name: usa-csc-526-by-spc
Version: 1.0.0
Summary: USA CSC 526 Final Project
Home-page: https://www.southalabama.edu/bulletin/current/courses/computer-science/index.html
Author: Stephen Paul Chappell
Author-email: spc2022@jagmail.southalabama.edu
License: Unlicense
Platform: UNKNOWN
License-File: LICENSE.txt
Requires-Dist: absl-py (==1.0.0)
Requires-Dist: astunparse (==1.6.3)
Requires-Dist: bleach (==4.1.0)
Requires-Dist: build (==0.7.0)
Requires-Dist: cachetools (==4.2.4)
Requires-Dist: certifi (==2021.10.8)
Requires-Dist: charset-normalizer (==2.0.8)
Requires-Dist: colorama (==0.4.4)
Requires-Dist: cycler (==0.11.0)
Requires-Dist: docutils (==0.18.1)
Requires-Dist: flatbuffers (==2.0)
Requires-Dist: fonttools (==4.28.2)
Requires-Dist: gast (==0.4.0)
Requires-Dist: google-auth (==2.3.3)
Requires-Dist: google-auth-oauthlib (==0.4.6)
Requires-Dist: google-pasta (==0.2.0)
Requires-Dist: grpcio (==1.42.0)
Requires-Dist: h5py (==3.6.0)
Requires-Dist: idna (==3.3)
Requires-Dist: importlib-metadata (==4.8.2)
Requires-Dist: joblib (==1.1.0)
Requires-Dist: keras (==2.7.0)
Requires-Dist: Keras-Preprocessing (==1.1.2)
Requires-Dist: keyring (==23.4.0)
Requires-Dist: kiwisolver (==1.3.2)
Requires-Dist: libclang (==12.0.0)
Requires-Dist: Markdown (==3.3.6)
Requires-Dist: matplotlib (==3.5.0)
Requires-Dist: numpy (==1.21.4)
Requires-Dist: oauthlib (==3.1.1)
Requires-Dist: opt-einsum (==3.3.0)
Requires-Dist: packaging (==21.3)
Requires-Dist: pep517 (==0.12.0)
Requires-Dist: Pillow (==8.4.0)
Requires-Dist: pkginfo (==1.8.2)
Requires-Dist: protobuf (==3.19.1)
Requires-Dist: pyasn1 (==0.4.8)
Requires-Dist: pyasn1-modules (==0.2.8)
Requires-Dist: Pygments (==2.10.0)
Requires-Dist: pyparsing (==3.0.6)
Requires-Dist: python-dateutil (==2.8.2)
Requires-Dist: pywin32-ctypes (==0.2.0)
Requires-Dist: readme-renderer (==30.0)
Requires-Dist: requests (==2.26.0)
Requires-Dist: requests-oauthlib (==1.3.0)
Requires-Dist: requests-toolbelt (==0.9.1)
Requires-Dist: rfc3986 (==1.5.0)
Requires-Dist: rsa (==4.8)
Requires-Dist: scikit-learn (==1.0.1)
Requires-Dist: scipy (==1.7.3)
Requires-Dist: setuptools-scm (==6.3.2)
Requires-Dist: six (==1.16.0)
Requires-Dist: tensorboard (==2.7.0)
Requires-Dist: tensorboard-data-server (==0.6.1)
Requires-Dist: tensorboard-plugin-wit (==1.8.0)
Requires-Dist: tensorflow (==2.7.0)
Requires-Dist: tensorflow-estimator (==2.7.0)
Requires-Dist: tensorflow-io-gcs-filesystem (==0.22.0)
Requires-Dist: termcolor (==1.1.0)
Requires-Dist: threadpoolctl (==3.0.0)
Requires-Dist: tomli (==1.2.2)
Requires-Dist: tqdm (==4.62.3)
Requires-Dist: twine (==3.7.0)
Requires-Dist: typing-extensions (==4.0.1)
Requires-Dist: urllib3 (==1.26.7)
Requires-Dist: webencodings (==0.5.1)
Requires-Dist: Werkzeug (==2.0.2)
Requires-Dist: wrapt (==1.13.3)
Requires-Dist: zipp (==3.6.0)
